DMCGui/__init__.py
DMCGui/src/build/settings/base.json
DMCGui/src/build/settings/linux.json
DMCGui/src/build/settings/mac.json
DMCGui/src/main/icons/Icon.ico
DMCGui/src/main/icons/README.md
DMCGui/src/main/icons/base/16.png
DMCGui/src/main/icons/base/24.png
DMCGui/src/main/icons/base/32.png
DMCGui/src/main/icons/base/48.png
DMCGui/src/main/icons/base/64.png
DMCGui/src/main/icons/linux/1024.png
DMCGui/src/main/icons/linux/128.png
DMCGui/src/main/icons/linux/256.png
DMCGui/src/main/icons/linux/512.png
DMCGui/src/main/icons/mac/1024.png
DMCGui/src/main/icons/mac/128.png
DMCGui/src/main/icons/mac/256.png
DMCGui/src/main/icons/mac/512.png
DMCGui/src/main/python/AboutDialog.py
DMCGui/src/main/python/AppContextEmulator.py
DMCGui/src/main/python/DMC_Data.py
DMCGui/src/main/python/DMC_GUI.py
DMCGui/src/main/python/DataModels.py
DMCGui/src/main/python/GuiStates.py
DMCGui/src/main/python/HelpDialog.py
DMCGui/src/main/python/LICENSE
DMCGui/src/main/python/README.md
DMCGui/src/main/python/StateMachine.py
DMCGui/src/main/python/_tools.py
DMCGui/src/main/python/generateScripts.py
DMCGui/src/main/python/main.py
DMCGui/src/main/python/Views/DataSetManager.py
DMCGui/src/main/python/Views/collapsibleBox.py
DMCGui/src/main/python/Views/dataOverviewManager.py
DMCGui/src/main/python/Views/main.py
DMCGui/src/main/python/Views/main.ui
DMCGui/src/main/resources/base/16.png
DMCGui/src/main/resources/base/24.png
DMCGui/src/main/resources/base/32.png
DMCGui/src/main/resources/base/48.png
DMCGui/src/main/resources/base/64.png
DMCGui/src/main/resources/base/About.txt
DMCGui/src/main/resources/base/Help.txt
DMCGui/src/main/resources/base/down.png
DMCGui/src/main/resources/base/right.png
DMCGui/src/main/resources/base/splash.png
DMCGui/src/main/resources/base/Icons/FILENAME.txt
DMCGui/src/main/resources/base/Icons/README.txt
DMCGui/src/main/resources/base/Icons/Own/CloseWindows.png
DMCGui/src/main/resources/base/Icons/Own/HDF_logo.png
DMCGui/src/main/resources/base/Icons/Own/HDF_logo_16.png
DMCGui-0.1.1.dist-info/LICENSE
DMCGui-0.1.1.dist-info/METADATA
DMCGui-0.1.1.dist-info/WHEEL
DMCGui-0.1.1.dist-info/entry_points.txt
DMCGui-0.1.1.dist-info/top_level.txt
DMCGui-0.1.1.dist-info/RECORD
