Metadata-Version: 2.1
Name: DMCGui
Version: 0.1.1
Summary: Neutron Scattering software suite.
Home-page: https://github.com/Jakob-Lass/DMCpy
Author: Jakob Lass
Author-email: jakob.lass@psi.ch
License: MPL-2.0
Platform: UNKNOWN
Classifier: Development Status :: 3 - Alpha
Classifier: Programming Language :: Python :: 3.6
Classifier: Programming Language :: Python :: 3.7
Classifier: Programming Language :: Python :: 3.8
Classifier: Programming Language :: Python :: 3.9
Requires-Python: >=3.5
Requires-Dist: pip (>=20)
Requires-Dist: sip (>=5.3)
Requires-Dist: PyQt5-sip
Requires-Dist: PyQt5
Requires-Dist: DMCPy (>=0.1.4)
